<?xml version="1.0" encoding="utf-8"?>
<RecordInfoDescriptor xmlns:xsd="http://www.w3.org/2001/XMLSchema" xmlns:xsi="http://www.w3.org/2001/XMLSchema-instance">
  <IntervalsList>
    <double>18.857999999999997</double>
    <double>1.1400000000000006</double>
    <double>3.4900000000000091</double>
    <double>2.7599999999999909</double>
    <double>0.24000000000000909</double>
    <double>0.22999999999998977</double>
    <double>2.7600000000000051</double>
    <double>1.6099999999999994</double>
    <double>2.7600000000000051</double>
    <double>0.21999999999999886</double>
    <double>2.3010000000000019</double>
    <double>2.9989999999999952</double>
    <double>0.21999999999999886</double>
    <double>1.3900000000000006</double>
    <double>0.5</double>
    <double>0.68000000000000682</double>
    <double>0.23999999999999488</double>
    <double>0.23000000000000398</double>
    <double>1.1439999999999912</double>
    <double>1.3800000000000097</double>
    <double>1.1599999999999966</double>
    <double>0.21999999999999886</double>
    <double>1.3799999999999955</double>
    <double>3.5</double>
    <double>0.23000000000000398</double>
    <double>0.68999999999999773</double>
    <double>0.23000000000000398</double>
    <double>0.23999999999999488</double>
    <double>0.92000000000000171</double>
    <double>0.45000000000000284</double>
    <double>1.6499999999999915</double>
    <double>0.69000000000001194</double>
    <double>0.22999999999998977</double>
    <double>4.13900000000001</double>
    <double>0.23099999999999454</double>
    <double>0.23999999999999488</double>
    <double>1.13900000000001</double>
    <double>0.45999999999999375</double>
    <double>0.24099999999999966</double>
    <double>0.2190000000000083</double>
    <double>0.45999999999999375</double>
    <double>0.45999999999999375</double>
    <double>0.23000000000000398</double>
    <double>1.1499999999999915</double>
    <double>0.46000000000000796</double>
    <double>0.46000000000000796</double>
    <double>0.23999999999998067</double>
    <double>0.92000000000001592</double>
    <double>0.21999999999999886</double>
    <double>0.46999999999999886</double>
    <double>1.1800000000000068</double>
    <double>0.68999999999999773</double>
    <double>0.69999999999998863</double>
    <double>3.6820000000000164</double>
    <double>0.91999999999998749</double>
    <double>0.68999999999999773</double>
    <double>0.45000000000001705</double>
    <double>0.681999999999988</double>
    <double>0.91999999999998749</double>
    <double>0.46000000000000796</double>
    <double>1.8400000000000034</double>
    <double>1.3799999999999955</double>
    <double>3.4500000000000171</double>
    <double>0.91899999999998272</double>
    <double>0.68999999999999773</double>
    <double>0.23099999999999454</double>
    <double>0.88000000000002387</double>
    <double>2.1189999999999998</double>
    <double>0.91999999999998749</double>
    <double>0.92000000000001592</double>
    <double>0.69099999999997408</double>
    <double>0.91900000000001114</double>
    <double>1.1409999999999911</double>
    <double>2.5400000000000205</double>
    <double>0.679000000000002</double>
    <double>1.1899999999999977</double>
    <double>0.22999999999998977</double>
    <double>1.1599999999999966</double>
    <double>8.4500000000000171</double>
    <double>0.75</double>
  </IntervalsList>
  <RecognitionsTimesList>
    <double>63.394</double>
    <double>82.252</double>
    <double>83.392</double>
    <double>86.882</double>
    <double>89.642</double>
    <double>89.882</double>
    <double>90.112</double>
    <double>92.872</double>
    <double>94.482</double>
    <double>97.242</double>
    <double>97.462</double>
    <double>99.763</double>
    <double>102.762</double>
    <double>102.982</double>
    <double>104.372</double>
    <double>104.872</double>
    <double>105.552</double>
    <double>105.792</double>
    <double>106.022</double>
    <double>107.166</double>
    <double>108.546</double>
    <double>109.706</double>
    <double>109.926</double>
    <double>111.306</double>
    <double>114.806</double>
    <double>115.036</double>
    <double>115.726</double>
    <double>115.956</double>
    <double>116.196</double>
    <double>117.116</double>
    <double>117.566</double>
    <double>119.216</double>
    <double>119.906</double>
    <double>120.136</double>
    <double>124.275</double>
    <double>124.506</double>
    <double>124.746</double>
    <double>125.885</double>
    <double>126.345</double>
    <double>126.586</double>
    <double>126.805</double>
    <double>127.265</double>
    <double>127.725</double>
    <double>127.955</double>
    <double>129.105</double>
    <double>129.565</double>
    <double>130.025</double>
    <double>130.265</double>
    <double>131.185</double>
    <double>131.405</double>
    <double>131.875</double>
    <double>133.055</double>
    <double>133.745</double>
    <double>134.445</double>
    <double>138.127</double>
    <double>139.047</double>
    <double>139.737</double>
    <double>140.187</double>
    <double>140.869</double>
    <double>141.789</double>
    <double>142.249</double>
    <double>144.089</double>
    <double>145.469</double>
    <double>148.919</double>
    <double>149.838</double>
    <double>150.528</double>
    <double>150.759</double>
    <double>151.639</double>
    <double>153.758</double>
    <double>154.678</double>
    <double>155.598</double>
    <double>156.289</double>
    <double>157.208</double>
    <double>158.349</double>
    <double>160.889</double>
    <double>161.568</double>
    <double>162.758</double>
    <double>162.988</double>
    <double>164.148</double>
    <double>172.598</double>
    <double>173.348</double>
  </RecognitionsTimesList>
  <AvgInterval>1.374425</AvgInterval>
  <MinInterval>0.2190000000000083</MinInterval>
  <MaxInterval>18.857999999999997</MaxInterval>
  <Duration>176.005</Duration>
  <LastSectionTimeSpan>3.9470000000000027</LastSectionTimeSpan>
  <LastSectionRecognitionsCount>2</LastSectionRecognitionsCount>
  <LastSectionMinInterval>0.75</LastSectionMinInterval>
  <LastSectionMaxInterval>0.75</LastSectionMaxInterval>
  <LastSectionAvgInterval>0.75</LastSectionAvgInterval>
</RecordInfoDescriptor>